argussight/__init__.py
argussight/__main__.py
argussight/core/config.py
argussight/core/configurations/config.yaml
argussight/core/configurations/processes/savers/stream_buffer.yaml
argussight/core/configurations/processes/savers/video_recorder.yaml
argussight/core/configurations/processes/savers/video_saver.yaml
argussight/core/configurations/processes/streamer/flow_detection.yaml
argussight/core/configurations/processes/streamer/optical_flow_detection.yaml
argussight/core/configurations/processes/streamer/streamer.yaml
argussight/core/configurations/processes/vprocess.yaml
argussight/core/helper_functions.py
argussight/core/manager.py
argussight/core/spawner.py
argussight/core/video_processes/savers/stream_buffer.py
argussight/core/video_processes/savers/video_recorder.py
argussight/core/video_processes/savers/video_saver.py
argussight/core/video_processes/streamer/flow_detection.py
argussight/core/video_processes/streamer/optical_flow_detection.py
argussight/core/video_processes/streamer/streamer.py
argussight/core/video_processes/vprocess.py
argussight/grpc/__init__.py
argussight/grpc/argus_service.proto
argussight/grpc/argus_service_pb2.py
argussight/grpc/argus_service_pb2_grpc.py
argussight/grpc/helper_functions.py
argussight/grpc/server.py
argussight/grpc/test_client.py
argussight/grpc/test_concurrent_requests.py
argussight/main.py
argussight/streamsproxy.py
argussight-0.1.0.dist-info/LICENSE
argussight-0.1.0.dist-info/METADATA
argussight-0.1.0.dist-info/WHEEL
argussight-0.1.0.dist-info/entry_points.txt
argussight-0.1.0.dist-info/RECORD
