Metadata-Version: 2.1
Name: argussight
Version: 0.1.0
Summary: An addition to MXCuBEWeb enabling simultaneous video streaming and distributed computer vision tasks.
Home-page: https://github.com/mxcube/argussight
License: MIT
Keywords: MXCuBEWeb,video streaming,computer vision,multistream,process management
Author: Yan Walesch
Author-email: <yan.walesch@esrf.fr
Requires-Python: >=3.10,<3.12
Classifier: License :: OSI Approved :: MIT License
Classifier: Programming Language :: Python :: 3
Classifier: Programming Language :: Python :: 3.10
Classifier: Programming Language :: Python :: 3.11
Requires-Dist: Flask (>=3.0.3,<4.0.0)
Requires-Dist: grpcio (>=1.38.0,<2.0.0)
Requires-Dist: grpcio-tools (>=1.38.0,<2.0.0)
Requires-Dist: mxcube-video-streamer (>=1.6.0)
Requires-Dist: numpy (>=1.26.0,<2.0.0)
Requires-Dist: opencv-python (==4.10.0.84)
Requires-Dist: pillow (>=9.4.0,<=10.4.0)
Requires-Dist: pydantic (>=2.8.2,<2.9.0)
Requires-Dist: python-levenshtein (>=0.25.1,<0.26.0)
Requires-Dist: pyyaml (>=6.0.1,<7.0.0)
Requires-Dist: redis (==4.6.0)
Requires-Dist: requests (>=2.32.3,<3.0.0)
Requires-Dist: websocket-client (>=1.8.0,<2.0.0)
Project-URL: Documentation, https://mxcube.github.io/argussight/
Project-URL: Repository, https://github.com/mxcube/argussight
